rstms_pymod/__init__.py
rstms_pymod/cli.py
rstms_pymod/exception_handler.py
rstms_pymod/project.py
rstms_pymod/shell.py
rstms_pymod/utils.py
rstms_pymod/version.py
rstms_pymod-0.0.5.dist-info/entry_points.txt
rstms_pymod-0.0.5.dist-info/LICENSE
rstms_pymod-0.0.5.dist-info/WHEEL
rstms_pymod-0.0.5.dist-info/METADATA
rstms_pymod-0.0.5.dist-info/RECORD
